[{"race_id": 7, "race_name": "Heart of the Hills Run", "date": "1981-07-18", "participant_name": "Dean Colprit", "centipede_names": "NULL", "runner_id": 0, "city": "", "state": "", "sex": "M", "overall_place": 1, "division": "Run", "age": "26", "age_group": "20-29", "time": "1:00:16"}, {"race_id": 7, "race_name": "Heart of the Hills Run", "date": "1981-07-18", "participant_name": "Homer Hastings", "centipede_names": "NULL", "runner_id": 0, "city": "", "state": "", "sex": "M", "overall_place": 2, "division": "Run", "age": "38", "age_group": "30-39", "time": "1:02:38"}, {"race_id": 7, "race_name": "Heart of the Hills Run", "date": "1981-07-18", "participant_name": "Rick Reeves", "centipede_names": "NULL", "runner_id": 0, "city": "", "state": "", "sex": "M", "overall_place": 3, "division": "Run", "age": "28", "age_group": "20-29", "time": "1:05:10"}, {"race_id": 7, "race_name": "Heart of the Hills Run", "date": "1981-07-18", "participant_name": "Don Oberle", "centipede_names": "NULL", "runner_id": 0, "city": "", "state": "", "sex": "M", "overall_place": 4, "division": "Run", "age": "2?", "age_group": "20-29", "time": "1:07:31"}, {"race_id": 7, "race_name": "Heart of the Hills Run", "date": "1981-07-18", "participant_name": "Jim Herdemann", "centipede_names": "NULL", "runner_id": 0, "city": "", "state": "", "sex": "M", "overall_place": 5, "division": "Run", "age": "??", "age_group": "Unknown", "time": "1:08:11"}, {"race_id": 7, "race_name": "Heart of the Hills Run", "date": "1981-07-18", "participant_name": "Steve Rice", "centipede_names": "NULL", "runner_id": 0, "city": "", "state": "", "sex": "M", "overall_place": 6, "division": "Run", "age": "??", "age_group": "Unknown", "time": "1:08:18"}, {"race_id": 7, "race_name": "Heart of the Hills Run", "date": "1981-07-18", "participant_name": "Loren Kambestad", "centipede_names": "NULL", "runner_id": 0, "city": "", "state": "", "sex": "M", "overall_place": 7, "division": "Run", "age": "30", "age_group": "30-39", "time": "1:08:41"}, {"race_id": 7, "race_name": "Heart of the Hills Run", "date": "1981-07-18", "participant_name": "Sergei Schmidt", "centipede_names": "NULL", "runner_id": 0, "city": "", "state": "", "sex": "M", "overall_place": 8, "division": "Run", "age": "??", "age_group": "Unknown", "time": "1:08:45"}, {"race_id": 7, "race_name": "Heart of the Hills Run", "date": "1981-07-18", "participant_name": "Bruce Renner", "centipede_names": "NULL", "runner_id": 0, "city": "", "state": "", "sex": "M", "overall_place": 9, "division": "Run", "age": "30", "age_group": "30-39", "time": "1:09:25"}, {"race_id": 7, "race_name": "Heart of the Hills Run", "date": "1981-07-18", "participant_name": "Todd Stevens", "centipede_names": "NULL", "runner_id": 0, "city": "", "state": "", "sex": "M", "overall_place": 10, "division": "Run", "age": "1?", "age_group": "Unknown", "time": "1:09:35"}, {"race_id": 7, "race_name": "Heart of the Hills Run", "date": "1981-07-18", "participant_name": "Rogg Burgess", "centipede_names": "NULL", "runner_id": 0, "city": "", "state": "", "sex": "M", "overall_place": 11, "division": "Run", "age": "??", "age_group": "Unknown", "time": "1:09:38"}, {"race_id": 7, "race_name": "Heart of the Hills Run", "date": "1981-07-18", "participant_name": "Gary Miller", "centipede_names": "NULL", "runner_id": 0, "city": "", "state": "", "sex": "M", "overall_place": 12, "division": "Run", "age": "26", "age_group": "20-29", "time": "1:09:54"}, {"race_id": 7, "race_name": "Heart of the Hills Run", "date": "1981-07-18", "participant_name": "Jim Withers", "centipede_names": "NULL", "runner_id": 0, "city": "", "state": "", "sex": "M", "overall_place": 13, "division": "Run", "age": "??", "age_group": "Unknown", "time": "1:10:10"}, {"race_id": 7, "race_name": "Heart of the Hills Run", "date": "1981-07-18", "participant_name": "Rich Barrows", "centipede_names": "NULL", "runner_id": 0, "city": "", "state": "", "sex": "M", "overall_place": 14, "division": "Run", "age": "21", "age_group": "20-29", "time": "1:10:47"}, {"race_id": 7, "race_name": "Heart of the Hills Run", "date": "1981-07-18", "participant_name": "Ken Pterbold", "centipede_names": "NULL", "runner_id": 0, "city": "", "state": "", "sex": "M", "overall_place": 15, "division": "Run", "age": "??", "age_group": "Unknown", "time": "1:11:08"}, {"race_id": 7, "race_name": "Heart of the Hills Run", "date": "1981-07-18", "participant_name": "David Lays Bad", "centipede_names": "NULL", "runner_id": 0, "city": "", "state": "", "sex": "M", "overall_place": 16, "division": "Run", "age": "18", "age_group": "16-19", "time": "1:11:53"}, {"race_id": 7, "race_name": "Heart of the Hills Run", "date": "1981-07-18", "participant_name": "John Houska", "centipede_names": "NULL", "runner_id": 0, "city": "", "state": "", "sex": "M", "overall_place": 17, "division": "Run", "age": "??", "age_group": "Unknown", "time": "1:12:24"}, {"race_id": 7, "race_name": "Heart of the Hills Run", "date": "1981-07-18", "participant_name": "Cliff Breck", "centipede_names": "NULL", "runner_id": 0, "city": "", "state": "", "sex": "M", "overall_place": 18, "division": "Run", "age": "??", "age_group": "Unknown", "time": "1:14:10"}, {"race_id": 7, "race_name": "Heart of the Hills Run", "date": "1981-07-18", "participant_name": "Mike Herdina", "centipede_names": "NULL", "runner_id": 0, "city": "", "state": "", "sex": "M", "overall_place": 19, "division": "Run", "age": "21", "age_group": "20-29", "time": "1:14:14"}, {"race_id": 7, "race_name": "Heart of the Hills Run", "date": "1981-07-18", "participant_name": "Bill Pullins", "centipede_names": "NULL", "runner_id": 0, "city": "", "state": "", "sex": "M", "overall_place": 20, "division": "Run", "age": "??", "age_group": "Unknown", "time": "1:14:34"}, {"race_id": 7, "race_name": "Heart of the Hills Run", "date": "1981-07-18", "participant_name": "Bruce Halla", "centipede_names": "NULL", "runner_id": 0, "city": "", "state": "", "sex": "M", "overall_place": 21, "division": "Run", "age": "??", "age_group": "Unknown", "time": "1:15:43"}, {"race_id": 7, "race_name": "Heart of the Hills Run", "date": "1981-07-18", "participant_name": "Dennis Lays Bad", "centipede_names": "NULL", "runner_id": 0, "city": "", "state": "", "sex": "M", "overall_place": 22, "division": "Run", "age": "??", "age_group": "Unknown", "time": "1:15:50"}, {"race_id": 7, "race_name": "Heart of the Hills Run", "date": "1981-07-18", "participant_name": "Linda Goddard", "centipede_names": "NULL", "runner_id": 0, "city": "", "state": "", "sex": "F", "overall_place": 23, "division": "Run", "age": "??", "age_group": "Unknown", "time": "1:15:51"}, {"race_id": 7, "race_name": "Heart of the Hills Run", "date": "1981-07-18", "participant_name": "Tom Hilt", "centipede_names": "NULL", "runner_id": 0, "city": "", "state": "", "sex": "M", "overall_place": 24, "division": "Run", "age": "1?", "age_group": "Unknown", "time": "1:15:03"}, {"race_id": 7, "race_name": "Heart of the Hills Run", "date": "1981-07-18", "participant_name": "Clyde Millslagle", "centipede_names": "NULL", "runner_id": 0, "city": "", "state": "", "sex": "M", "overall_place": 25, "division": "Run", "age": "??", "age_group": "Unknown", "time": "1:16:30"}, {"race_id": 7, "race_name": "Heart of the Hills Run", "date": "1981-07-18", "participant_name": "Rick Walter", "centipede_names": "NULL", "runner_id": 0, "city": "", "state": "", "sex": "M", "overall_place": 26, "division": "Run", "age": "30", "age_group": "30-39", "time": "1:18:23"}, {"race_id": 7, "race_name": "Heart of the Hills Run", "date": "1981-07-18", "participant_name": "Curt Ireland", "centipede_names": "NULL", "runner_id": 0, "city": "", "state": "", "sex": "M", "overall_place": 27, "division": "Run", "age": "47", "age_group": "40-49", "time": "1:19:36"}, {"race_id": 7, "race_name": "Heart of the Hills Run", "date": "1981-07-18", "participant_name": "Bernie Finch", "centipede_names": "NULL", "runner_id": 0, "city": "", "state": "", "sex": "M", "overall_place": 28, "division": "Run", "age": "41", "age_group": "40-49", "time": "1:19:36"}, {"race_id": 7, "race_name": "Heart of the Hills Run", "date": "1981-07-18", "participant_name": "John McDill", "centipede_names": "NULL", "runner_id": 0, "city": "", "state": "", "sex": "M", "overall_place": 29, "division": "Run", "age": "??", "age_group": "Unknown", "time": "1:20:08"}, {"race_id": 7, "race_name": "Heart of the Hills Run", "date": "1981-07-18", "participant_name": "Cindy Sargent", "centipede_names": "NULL", "runner_id": 0, "city": "", "state": "", "sex": "F", "overall_place": 30, "division": "Run", "age": "20", "age_group": "20-29", "time": "1:30:50"}, {"race_id": 7, "race_name": "Heart of the Hills Run", "date": "1981-07-18", "participant_name": "Tim Whalen", "centipede_names": "NULL", "runner_id": 0, "city": "", "state": "", "sex": "M", "overall_place": 31, "division": "Run", "age": "??", "age_group": "Unknown", "time": "1:20:50"}, {"race_id": 7, "race_name": "Heart of the Hills Run", "date": "1981-07-18", "participant_name": "Don Polovich", "centipede_names": "NULL", "runner_id": 0, "city": "", "state": "", "sex": "M", "overall_place": 32, "division": "Run", "age": "??", "age_group": "Unknown", "time": "1:21:34"}, {"race_id": 7, "race_name": "Heart of the Hills Run", "date": "1981-07-18", "participant_name": "Lonnie Morris", "centipede_names": "NULL", "runner_id": 0, "city": "", "state": "", "sex": "M", "overall_place": 33, "division": "Run", "age": "??", "age_group": "Unknown", "time": "1:21:55"}, {"race_id": 7, "race_name": "Heart of the Hills Run", "date": "1981-07-18", "participant_name": "Craig Groseth", "centipede_names": "NULL", "runner_id": 0, "city": "", "state": "", "sex": "M", "overall_place": 34, "division": "Run", "age": "??", "age_group": "Unknown", "time": "1:22:37"}, {"race_id": 7, "race_name": "Heart of the Hills Run", "date": "1981-07-18", "participant_name": "Mike Ritchard", "centipede_names": "NULL", "runner_id": 0, "city": "", "state": "", "sex": "M", "overall_place": 35, "division": "Run", "age": "??", "age_group": "Unknown", "time": "1:23:02"}, {"race_id": 7, "race_name": "Heart of the Hills Run", "date": "1981-07-18", "participant_name": "Rick Cordes", "centipede_names": "NULL", "runner_id": 0, "city": "", "state": "", "sex": "M", "overall_place": 36, "division": "Run", "age": "??", "age_group": "Unknown", "time": "1:23:37"}, {"race_id": 7, "race_name": "Heart of the Hills Run", "date": "1981-07-18", "participant_name": "Wes Wilsey", "centipede_names": "NULL", "runner_id": 0, "city": "", "state": "", "sex": "M", "overall_place": 37, "division": "Run", "age": "48", "age_group": "40-49", "time": "1:24:29"}, {"race_id": 7, "race_name": "Heart of the Hills Run", "date": "1981-07-18", "participant_name": "Dale Pine", "centipede_names": "NULL", "runner_id": 0, "city": "", "state": "", "sex": "M", "overall_place": 38, "division": "Run", "age": "??", "age_group": "Unknown", "time": "1:26:01"}, {"race_id": 7, "race_name": "Heart of the Hills Run", "date": "1981-07-18", "participant_name": "Dennis Lunsford", "centipede_names": "NULL", "runner_id": 0, "city": "", "state": "", "sex": "M", "overall_place": 39, "division": "Run", "age": "35", "age_group": "30-39", "time": "1:26:16"}, {"race_id": 7, "race_name": "Heart of the Hills Run", "date": "1981-07-18", "participant_name": "Bob Bailey", "centipede_names": "NULL", "runner_id": 0, "city": "", "state": "", "sex": "M", "overall_place": 40, "division": "Run", "age": "??", "age_group": "Unknown", "time": "1:26:24"}, {"race_id": 7, "race_name": "Heart of the Hills Run", "date": "1981-07-18", "participant_name": "Dave Lyons", "centipede_names": "NULL", "runner_id": 0, "city": "", "state": "", "sex": "M", "overall_place": 41, "division": "Run", "age": "33", "age_group": "30-39", "time": "1:26:36"}, {"race_id": 7, "race_name": "Heart of the Hills Run", "date": "1981-07-18", "participant_name": "Tom Young", "centipede_names": "NULL", "runner_id": 0, "city": "", "state": "", "sex": "M", "overall_place": 42, "division": "Run", "age": "18", "age_group": "16-19", "time": "1:27:00"}, {"race_id": 7, "race_name": "Heart of the Hills Run", "date": "1981-07-18", "participant_name": "John Notheis", "centipede_names": "NULL", "runner_id": 0, "city": "", "state": "", "sex": "M", "overall_place": 43, "division": "Run", "age": "49", "age_group": "40-49", "time": "1:27:21"}, {"race_id": 7, "race_name": "Heart of the Hills Run", "date": "1981-07-18", "participant_name": "Gary Welsh", "centipede_names": "NULL", "runner_id": 0, "city": "", "state": "", "sex": "M", "overall_place": 44, "division": "Run", "age": "??", "age_group": "Unknown", "time": "1:27:28"}, {"race_id": 7, "race_name": "Heart of the Hills Run", "date": "1981-07-18", "participant_name": "Patrick McCreal", "centipede_names": "NULL", "runner_id": 0, "city": "", "state": "", "sex": "M", "overall_place": 45, "division": "Run", "age": "??", "age_group": "Unknown", "time": "1:27:43"}, {"race_id": 7, "race_name": "Heart of the Hills Run", "date": "1981-07-18", "participant_name": "Doyle Nehl", "centipede_names": "NULL", "runner_id": 0, "city": "", "state": "", "sex": "M", "overall_place": 46, "division": "Run", "age": "31", "age_group": "30-39", "time": "1:27:44"}, {"race_id": 7, "race_name": "Heart of the Hills Run", "date": "1981-07-18", "participant_name": "Elaine Hutspinler", "centipede_names": "NULL", "runner_id": 0, "city": "", "state": "", "sex": "F", "overall_place": 47, "division": "Run", "age": "43", "age_group": "40-49", "time": "1:28:05"}, {"race_id": 7, "race_name": "Heart of the Hills Run", "date": "1981-07-18", "participant_name": "Tim Tennessen", "centipede_names": "NULL", "runner_id": 0, "city": "", "state": "", "sex": "M", "overall_place": 48, "division": "Run", "age": "??", "age_group": "Unknown", "time": "1:29:31"}, {"race_id": 7, "race_name": "Heart of the Hills Run", "date": "1981-07-18", "participant_name": "Dennis Park", "centipede_names": "NULL", "runner_id": 0, "city": "", "state": "", "sex": "M", "overall_place": 49, "division": "Run", "age": "??", "age_group": "Unknown", "time": "1:29:48"}, {"race_id": 7, "race_name": "Heart of the Hills Run", "date": "1981-07-18", "participant_name": "Sam Graham", "centipede_names": "NULL", "runner_id": 0, "city": "", "state": "", "sex": "M", "overall_place": 50, "division": "Run", "age": "??", "age_group": "Unknown", "time": "1:30:55"}, {"race_id": 7, "race_name": "Heart of the Hills Run", "date": "1981-07-18", "participant_name": "Steve Warren", "centipede_names": "NULL", "runner_id": 0, "city": "", "state": "", "sex": "M", "overall_place": 51, "division": "Run", "age": "??", "age_group": "Unknown", "time": "1:32:30"}, {"race_id": 7, "race_name": "Heart of the Hills Run", "date": "1981-07-18", "participant_name": "Karen Nehl", "centipede_names": "NULL", "runner_id": 0, "city": "", "state": "", "sex": "F", "overall_place": 52, "division": "Run", "age": "31", "age_group": "30-39", "time": "1:33:10"}, {"race_id": 7, "race_name": "Heart of the Hills Run", "date": "1981-07-18", "participant_name": "Lynn Wilson", "centipede_names": "NULL", "runner_id": 0, "city": "", "state": "", "sex": "F", "overall_place": 53, "division": "Run", "age": "??", "age_group": "Unknown", "time": "1:34:22"}, {"race_id": 7, "race_name": "Heart of the Hills Run", "date": "1981-07-18", "participant_name": "Chris Ross", "centipede_names": "NULL", "runner_id": 0, "city": "", "state": "", "sex": "M", "overall_place": 54, "division": "Run", "age": "??", "age_group": "Unknown", "time": "1:34:26"}, {"race_id": 7, "race_name": "Heart of the Hills Run", "date": "1981-07-18", "participant_name": "Brad Knudsen", "centipede_names": "NULL", "runner_id": 0, "city": "", "state": "", "sex": "M", "overall_place": 55, "division": "Run", "age": "??", "age_group": "Unknown", "time": "1:37:54"}, {"race_id": 7, "race_name": "Heart of the Hills Run", "date": "1981-07-18", "participant_name": "George Dunkelbar", "centipede_names": "NULL", "runner_id": 0, "city": "", "state": "", "sex": "M", "overall_place": 56, "division": "Run", "age": "??", "age_group": "Unknown", "time": "1:38:04"}, {"race_id": 7, "race_name": "Heart of the Hills Run", "date": "1981-07-18", "participant_name": "Elaine Doll-Dunn", "centipede_names": "NULL", "runner_id": 0, "city": "", "state": "", "sex": "F", "overall_place": 57, "division": "Run", "age": "43", "age_group": "40-49", "time": "1:38:45"}, {"race_id": 7, "race_name": "Heart of the Hills Run", "date": "1981-07-18", "participant_name": "Frank Page", "centipede_names": "NULL", "runner_id": 0, "city": "", "state": "", "sex": "M", "overall_place": 58, "division": "Run", "age": "47", "age_group": "40-49", "time": "1:39:01"}, {"race_id": 7, "race_name": "Heart of the Hills Run", "date": "1981-07-18", "participant_name": "Mike McGinnis", "centipede_names": "NULL", "runner_id": 0, "city": "", "state": "", "sex": "M", "overall_place": 59, "division": "Run", "age": "??", "age_group": "Unknown", "time": "1:41:36"}, {"race_id": 7, "race_name": "Heart of the Hills Run", "date": "1981-07-18", "participant_name": "Tracy Whalen", "centipede_names": "NULL", "runner_id": 0, "city": "", "state": "", "sex": "F", "overall_place": 60, "division": "Run", "age": "??", "age_group": "Unknown", "time": "1:42:35"}, {"race_id": 7, "race_name": "Heart of the Hills Run", "date": "1981-07-18", "participant_name": "Kristi Coyle", "centipede_names": "NULL", "runner_id": 0, "city": "", "state": "", "sex": "F", "overall_place": 61, "division": "Run", "age": "1?", "age_group": "Unknown", "time": "1:57:39"}, {"race_id": 7, "race_name": "Heart of the Hills Run", "date": "1981-07-18", "participant_name": "Tom Casey", "centipede_names": "NULL", "runner_id": 0, "city": "", "state": "", "sex": "M", "overall_place": 62, "division": "Run", "age": "??", "age_group": "Unknown", "time": "1:57:59"}, {"race_id": 7, "race_name": "Heart of the Hills Run", "date": "1981-07-18", "participant_name": "Ed Howell", "centipede_names": "NULL", "runner_id": 0, "city": "", "state": "", "sex": "M", "overall_place": 63, "division": "Run", "age": "??", "age_group": "Unknown", "time": "2:00:42"}, {"race_id": 7, "race_name": "Heart of the Hills Run", "date": "1981-07-18", "participant_name": "Pat Howell", "centipede_names": "NULL", "runner_id": 0, "city": "", "state": "", "sex": "F", "overall_place": 64, "division": "Run", "age": "??", "age_group": "Unknown", "time": "2:02:15"}, {"race_id": 7, "race_name": "Heart of the Hills Run", "date": "1981-07-18", "participant_name": "Arnie Finch", "centipede_names": "NULL", "runner_id": 0, "city": "", "state": "", "sex": "M", "overall_place": 65, "division": "Run", "age": "1?", "age_group": "Unknown", "time": "2:04:02"}, {"race_id": 7, "race_name": "Heart of the Hills Run", "date": "1981-07-18", "participant_name": "Doug Treiock", "centipede_names": "NULL", "runner_id": 0, "city": "", "state": "", "sex": "M", "overall_place": 66, "division": "Run", "age": "??", "age_group": "Unknown", "time": "2:07:21"}]